[
  { "query_display": "孙颖莎4-0王艺迪", "real_query": "孙颖莎4-0王艺迪" },
  { "query_display": "中央经济工作会议举行", "real_query": "中央经济工作会议举行" },
  { "query_display": "美联储降息25个基点", "real_query": "美联储降息25个基点" },
  { "query_display": "红楼梦", "real_query": "红楼梦" },
  { "query_display": "bba车主最后的体面被盒饭击溃", "real_query": "bba车主最后的体面被盒饭击溃" },
  {
    "query_display": "你对马克龙在四川大学演讲中的建议有何感悟",
    "real_query": "你对马克龙在四川大学演讲中的建议有何感悟"
  },
  { "query_display": "中国贸易顺差首次超1万亿美元", "real_query": "中国贸易顺差首次超1万亿美元" },
  { "query_display": "红楼梦索隐派", "real_query": "红楼梦索隐派" },
  { "query_display": "范曾官宣得子 与女儿继子断绝关系", "real_query": "范曾官宣得子 与女儿继子断绝关系" },
  { "query_display": "男子在路边发现疑似冬眠的眼镜蛇", "real_query": "男子在路边发现疑似冬眠的眼镜蛇" },
  { "query_display": "多家APP对豆包手机禁用", "real_query": "多家APP对豆包手机禁用" },
  { "query_display": "多校撤销外语专业", "real_query": "多校撤销外语专业" },
  { "query_display": "2026春晚官宣", "real_query": "2026春晚官宣" },
  { "query_display": "众擎机器人完成踹人动作有哪些技术亮点", "real_query": "众擎机器人完成踹人动作有哪些技术亮点" },
  { "query_display": "淘宝闪购取消外卖超时扣款有何影响", "real_query": "淘宝闪购取消外卖超时扣款有何影响" },
  { "query_display": "比利时 15 岁少年获量子物理学博士学位", "real_query": "比利时 15 岁少年获量子物理学博士学位" },
  { "query_display": "什么东西曾经离谱的贵现在却非常便宜", "real_query": "什么东西曾经离谱的贵现在却非常便宜" }
]
