[
  { "query_display": "金价银价急跌", "real_query": "金价银价急跌" },
  { "query_display": "韩国梨泰院踩踏惨案调查结果公布", "real_query": "韩国梨泰院踩踏惨案调查结果公布" },
  { "query_display": "十五五目标", "real_query": "十五五目标" },
  { "query_display": "多地中小学生11月喜提5天小长假", "real_query": "多地中小学生11月喜提5天小长假" },
  { "query_display": "导师给你的最后忠告是什么", "real_query": "导师给你的最后忠告是什么" },
  { "query_display": "CSGO游戏更新导致游戏外市场崩溃", "real_query": "CSGO游戏更新导致游戏外市场崩溃" },
  { "query_display": "王自如自曝负债 1 个亿", "real_query": "王自如自曝负债 1 个亿" },
  { "query_display": "十五五规划建议审议通过", "real_query": "十五五规划建议审议通过" },
  { "query_display": "卢浮宫的安防系统存在哪些漏洞", "real_query": "卢浮宫的安防系统存在哪些漏洞" },
  { "query_display": "GEN 2:0 TES", "real_query": "GEN 2:0 TES" },
  { "query_display": "宗馥莉重新启用娃哈哈品牌", "real_query": "宗馥莉重新启用娃哈哈品牌" },
  { "query_display": "如何评价丘成桐的《悼念杨振宁教授》一联", "real_query": "如何评价丘成桐的《悼念杨振宁教授》一联" },
  { "query_display": "你喝多了都干过什么蠢事", "real_query": "你喝多了都干过什么蠢事" },
  { "query_display": "男童掉进烧烤店炭堆全身烧伤", "real_query": "男童掉进烧烤店炭堆全身烧伤" },
  { "query_display": "小学女儿同学借给她衣服穿收两元怎么教育", "real_query": "小学女儿同学借给她衣服穿收两元怎么教育" },
  { "query_display": "沙县鸡腿饭成年轻人减肥餐", "real_query": "沙县鸡腿饭成年轻人减肥餐" },
  { "query_display": "遭美国网络攻击的「北京时间」是什么", "real_query": "遭美国网络攻击的「北京时间」是什么" },
  { "query_display": "如何看待于东来称「胖东来是怪胎」", "real_query": "如何看待于东来称「胖东来是怪胎」" },
  { "query_display": "闻泰科技147亿半导体资产被荷兰冻结", "real_query": "闻泰科技147亿半导体资产被荷兰冻结" },
  { "query_display": "什么叫中国人的浪漫", "real_query": "什么叫中国人的浪漫" },
  { "query_display": "有可能以后飞机用电不用油吗", "real_query": "有可能以后飞机用电不用油吗" },
  { "query_display": "阿里巴巴与蚂蚁集团拟斥资买楼设香港总部", "real_query": "阿里巴巴与蚂蚁集团拟斥资买楼设香港总部" },
  { "query_display": "如何看待美国大豆田没人收割", "real_query": "如何看待美国大豆田没人收割" },
  { "query_display": "女子集市上免费洗金镯被洗掉5克", "real_query": "女子集市上免费洗金镯被洗掉5克" },
  { "query_display": "某农商行员工爆料称被要求退回三年过节费", "real_query": "某农商行员工爆料称被要求退回三年过节费" },
  { "query_display": "特朗普起诉特朗普政府", "real_query": "特朗普起诉特朗普政府" },
  { "query_display": "不用中考十二年贯通式学校来了", "real_query": "不用中考十二年贯通式学校来了" },
  { "query_display": "船员严重晕船后自缢身亡家属索赔被驳回", "real_query": "船员严重晕船后自缢身亡家属索赔被驳回" },
  { "query_display": "有个亲妹妹是什么感觉", "real_query": "有个亲妹妹是什么感觉" },
  { "query_display": "王天一致歉信称自己屠龙少年成恶龙", "real_query": "王天一致歉信称自己屠龙少年成恶龙" },
  { "query_display": "美国治安已经差到这么离谱了吗", "real_query": "美国治安已经差到这么离谱了吗" },
  { "query_display": "美国多地举行「不要国王」抗议活动", "real_query": "美国多地举行「不要国王」抗议活动" },
  { "query_display": "多家银行将清理长期不动账户", "real_query": "多家银行将清理长期不动账户" },
  { "query_display": "鸿蒙 6 正式发布", "real_query": "鸿蒙 6 正式发布" },
  { "query_display": "男子在靠近长白山沿途偶遇东北虎", "real_query": "男子在靠近长白山沿途偶遇东北虎" },
  { "query_display": "林草局介入多人在草原抛纸片事件", "real_query": "林草局介入多人在草原抛纸片事件" },
  { "query_display": "GEN对战TES", "real_query": "GEN对战TES" }
]
