[
  { "query_display": "张碧晨方称享有年轮永久演唱权利", "real_query": "张碧晨方称享有年轮永久演唱权利" },
  { "query_display": "6名大学生溺亡涉事矿企3人被抓", "real_query": "6名大学生溺亡涉事矿企3人被抓" },
  { "query_display": "国务院部署逐步推行免费学前教育", "real_query": "国务院部署逐步推行免费学前教育" },
  { "query_display": "懂车帝封闭高速辅助驾驶测试", "real_query": "懂车帝封闭高速辅助驾驶测试" },
  { "query_display": "汪苏泷张碧晨《年轮》原唱之争", "real_query": "汪苏泷张碧晨《年轮》原唱之争" },
  { "query_display": "于正称没有再联系街拍女孩七七了", "real_query": "于正称没有再联系街拍女孩七七了" },
  { "query_display": "泰国与柬埔寨发生交火", "real_query": "泰国与柬埔寨发生交火" },
  { "query_display": "华东理工大学被指抄袭南昌大学录取通知书", "real_query": "华东理工大学被指抄袭南昌大学录取通知书" },
  { "query_display": "撞脸张柏芝女孩商场站台2小时8千元", "real_query": "撞脸张柏芝女孩商场站台2小时8千元" },
  { "query_display": "张碧晨不会再唱年轮", "real_query": "张碧晨不会再唱年轮" },
  { "query_display": "6名大学生在企业参观学习时溺亡", "real_query": "6名大学生在企业参观学习时溺亡" },
  { "query_display": "樊振东 3-0 林诗栋", "real_query": "樊振东 3-0 林诗栋" }
]
