[
  { "query_display": "那尔那茜涉嫌高考报名材料造假", "real_query": "那尔那茜涉嫌高考报名材料造假" },
  { "query_display": "美国袭击伊朗核设施", "real_query": "美国袭击伊朗核设施" },
  { "query_display": "美军轰炸伊朗福尔多核设施", "real_query": "美军轰炸伊朗福尔多核设施" },
  { "query_display": "王欣瑜对阵万卓索娃", "real_query": "王欣瑜对阵万卓索娃" },
  { "query_display": "特朗普称打击伊朗3处核设施", "real_query": "特朗普称打击伊朗3处核设施" },
  { "query_display": "特朗普要求伊朗无条件投降有哪些目的", "real_query": "特朗普要求伊朗无条件投降有哪些目的" },
  { "query_display": "英舰过航台湾海峡", "real_query": "英舰过航台湾海峡" },
  { "query_display": "特朗普称伊朗核设施已彻底摧毁", "real_query": "特朗普称伊朗核设施已彻底摧毁" },
  { "query_display": "伊朗核设施遭袭画面公开", "real_query": "伊朗核设施遭袭画面公开" },
  { "query_display": "你见过哪些很有创意的高考应援", "real_query": "你见过哪些很有创意的高考应援" },
  { "query_display": "伊朗与英法德密谈3小时", "real_query": "伊朗与英法德密谈3小时" },
  { "query_display": "陈楚生第一", "real_query": "陈楚生第一" },
  { "query_display": "如何看待 AL 的冠军被改成优胜者", "real_query": "如何看待 AL 的冠军被改成优胜者" },
  { "query_display": "何为「休克疗法」", "real_query": "何为「休克疗法」" },
  { "query_display": "张子宇会是下一个「姚明」吗", "real_query": "张子宇会是下一个「姚明」吗" },
  { "query_display": "男孩结婚2小时后坠亡婚姻被判无效", "real_query": "男孩结婚2小时后坠亡婚姻被判无效" },
  { "query_display": "西安一商场大屏播放巨大电风扇", "real_query": "西安一商场大屏播放巨大电风扇" },
  { "query_display": "周杰伦被曝现身日本弯腰驼背似老人", "real_query": "周杰伦被曝现身日本弯腰驼背似老人" },
  { "query_display": "京东正式进军酒旅市场", "real_query": "京东正式进军酒旅市场" },
  { "query_display": "以方已摧毁伊朗铀浓缩设施", "real_query": "以方已摧毁伊朗铀浓缩设施" },
  {
    "query_display": "哈梅内伊称不接受任何「强加的和平或战争」",
    "real_query": "哈梅内伊称不接受任何「强加的和平或战争」"
  },
  { "query_display": "湖南又一溶洞被曝遍布垃圾", "real_query": "湖南又一溶洞被曝遍布垃圾" },
  { "query_display": "张爱玲教授逝世", "real_query": "张爱玲教授逝世" },
  { "query_display": "救护车八百公里收费 2.8 万元合理吗", "real_query": "救护车八百公里收费 2.8 万元合理吗" },
  { "query_display": "清华回应女教授被树砸身亡", "real_query": "清华回应女教授被树砸身亡" },
  { "query_display": "若李雪琴公司财务问题属实需承担哪些责任", "real_query": "若李雪琴公司财务问题属实需承担哪些责任" },
  { "query_display": "「苏超」爆火做对了什么", "real_query": "「苏超」爆火做对了什么" },
  { "query_display": "内蒙古教育厅回应那尔那茜定向委培事件", "real_query": "内蒙古教育厅回应那尔那茜定向委培事件" },
  { "query_display": "如何看待朱丹的育儿观", "real_query": "如何看待朱丹的育儿观" },
  { "query_display": "以军要求以全境民众进避难所", "real_query": "以军要求以全境民众进避难所" },
  { "query_display": "你在部队捅过最大的娄子是什么", "real_query": "你在部队捅过最大的娄子是什么" },
  { "query_display": "刘强东称京东外卖会出一个不同的商业模式", "real_query": "刘强东称京东外卖会出一个不同的商业模式" }
]
