[
  { "query_display": "商务部加强对日两用物项出口管制", "real_query": "商务部加强对日两用物项出口管制" },
  { "query_display": "美军强掳马杜罗", "real_query": "美军强掳马杜罗" },
  { "query_display": "特朗普下令空袭委内瑞拉", "real_query": "特朗普下令空袭委内瑞拉" },
  { "query_display": "霸王茶姬店员「手打」饮品", "real_query": "霸王茶姬店员「手打」饮品" },
  { "query_display": "武大靖官宣退役", "real_query": "武大靖官宣退役" },
  { "query_display": "2025年十大语文差错公布", "real_query": "2025年十大语文差错公布" },
  { "query_display": "小米公关部徐洁云发文致歉", "real_query": "小米公关部徐洁云发文致歉" },
  { "query_display": "委内瑞拉发生了什么", "real_query": "委内瑞拉发生了什么" },
  { "query_display": "农村不允许烧煤如何取暖", "real_query": "农村不允许烧煤如何取暖" },
  { "query_display": "三体预言美国入侵委内瑞拉", "real_query": "三体预言美国入侵委内瑞拉" },
  { "query_display": "新生儿剪脐带时被剪断手指", "real_query": "新生儿剪脐带时被剪断手指" },
  { "query_display": "小洛熙爸爸回应病历真假认定", "real_query": "小洛熙爸爸回应病历真假认定" }
]
