[
  { "query_display": "伊朗局势", "real_query": "伊朗局势" },
  { "query_display": "NASA 阿尔忒弥斯 2 号载人绕月飞行", "real_query": "NASA 阿尔忒弥斯 2 号载人绕月飞行" },
  { "query_display": "王楚钦逆转晋级世界杯四强", "real_query": "王楚钦逆转晋级世界杯四强" },
  { "query_display": "工信部提醒苹果iOS高危漏洞", "real_query": "工信部提醒苹果iOS高危漏洞" },
  { "query_display": "韩国 40 岁导演遭围殴致死引发众怒", "real_query": "韩国 40 岁导演遭围殴致死引发众怒" },
  { "query_display": "幼儿园闭园后幼师再就业成难题", "real_query": "幼儿园闭园后幼师再就业成难题" },
  { "query_display": "浪姐 7 初舞台直播", "real_query": "浪姐 7 初舞台直播" },
  { "query_display": "美官员说失踪飞行员已找到", "real_query": "美官员说失踪飞行员已找到" },
  { "query_display": "何小鹏称不碰10万以下汽车", "real_query": "何小鹏称不碰10万以下汽车" },
  { "query_display": "同事.skill爆火", "real_query": "同事.skill爆火" },
  { "query_display": "清明节", "real_query": "清明节" },
  { "query_display": "美军一天内两架战机被伊朗击落", "real_query": "美军一天内两架战机被伊朗击落" },
  { "query_display": "现在的小孩可以早熟到什么地步", "real_query": "现在的小孩可以早熟到什么地步" },
  { "query_display": "新版雷克萨斯 es 为何看上去一言难尽", "real_query": "新版雷克萨斯 es 为何看上去一言难尽" },
  { "query_display": "如何看待高校 4:30 锁教学楼", "real_query": "如何看待高校 4:30 锁教学楼" },
  {
    "query_display": "为什么动物的毛发不会像人类一样不停地生长",
    "real_query": "为什么动物的毛发不会像人类一样不停地生长"
  },
  { "query_display": "鹈鹕真的没有攻击力吗", "real_query": "鹈鹕真的没有攻击力吗" },
  { "query_display": "日本一拉面店禁看手机", "real_query": "日本一拉面店禁看手机" },
  {
    "query_display": "你认为「张雪机车」的故事适不适合拍成电影",
    "real_query": "你认为「张雪机车」的故事适不适合拍成电影"
  },
  { "query_display": "突发，京东副总裁被开除", "real_query": "突发，京东副总裁被开除" },
  { "query_display": "天龙三号发射失利", "real_query": "天龙三号发射失利" },
  { "query_display": "武汉一男子持刀致4人受伤", "real_query": "武汉一男子持刀致4人受伤" },
  { "query_display": "绩效和 Token 消耗挂钩合理吗", "real_query": "绩效和 Token 消耗挂钩合理吗" },
  { "query_display": "武汉一高校内设置 999 秒红绿灯合理吗", "real_query": "武汉一高校内设置 999 秒红绿灯合理吗" },
  {
    "query_display": "如何看待「捧杀」与「棒杀」交替的饭圈怪圈",
    "real_query": "如何看待「捧杀」与「棒杀」交替的饭圈怪圈"
  },
  { "query_display": "苹果被曝高价扫荡全球手机内存", "real_query": "苹果被曝高价扫荡全球手机内存" },
  { "query_display": "伊朗：以色列袭击美驻沙特大使馆", "real_query": "伊朗：以色列袭击美驻沙特大使馆" },
  { "query_display": "孙颖莎4-3高达", "real_query": "孙颖莎4-3高达" },
  { "query_display": "清明", "real_query": "清明" },
  { "query_display": "张雪称影视版权给顶级团队", "real_query": "张雪称影视版权给顶级团队" }
]
