[
  { "query_display": "中美经贸磋商初步成果公布", "real_query": "中美经贸磋商初步成果公布" },
  { "query_display": "上海交大学生豆包伪造证据私吞奖金", "real_query": "上海交大学生豆包伪造证据私吞奖金" },
  { "query_display": "小马云13岁确诊智力二级残疾", "real_query": "小马云13岁确诊智力二级残疾" },
  { "query_display": "耿同学论文被反向打假", "real_query": "耿同学论文被反向打假" },
  { "query_display": "特朗普明确表态不希望台湾独立", "real_query": "特朗普明确表态不希望台湾独立" },
  { "query_display": "央视拿下世界杯版权", "real_query": "央视拿下世界杯版权" },
  { "query_display": "樊振东 vs 勒布伦兄弟", "real_query": "樊振东 vs 勒布伦兄弟" },
  { "query_display": "大摆荡释放开关提前打开致游客坠亡", "real_query": "大摆荡释放开关提前打开致游客坠亡" },
  { "query_display": "俄罗斯总统普京访华", "real_query": "俄罗斯总统普京访华" },
  { "query_display": "美国总统特朗普结束访华", "real_query": "美国总统特朗普结束访华" },
  { "query_display": "张雪机车拿下第五冠", "real_query": "张雪机车拿下第五冠" },
  { "query_display": "张雪机车夺WSBK第4冠", "real_query": "张雪机车夺WSBK第4冠" }
]
